awaiter/__init__.py
awaiter-0.1.1.dist-info/LICENSE
awaiter-0.1.1.dist-info/METADATA
awaiter-0.1.1.dist-info/WHEEL
awaiter-0.1.1.dist-info/top_level.txt
awaiter-0.1.1.dist-info/RECORD
