Metadata-Version: 2.1
Name: awaiter
Version: 0.1.1
Summary: Makes your blocking functions awaitable.
Author-email: nggit <contact@anggit.com>
License: MIT License
Project-URL: Homepage, https://github.com/nggit/awaiter
Project-URL: Source, https://github.com/nggit/awaiter
Project-URL: Funding, https://github.com/sponsors/nggit
Classifier: Development Status :: 4 - Beta
Classifier: Intended Audience :: Developers
Classifier: License :: OSI Approved :: MIT License
Classifier: Operating System :: OS Independent
Classifier: Topic :: Software Development :: Libraries
Classifier: Framework :: AsyncIO
Requires-Python: >=3.7
License-File: LICENSE
